{
    "puzzleId": "level-primary-fruit-003",
    "level_id": 3,
    "pack_id": "primary",
    "stage": "primary",
    "theme": "水果",
    "theme_en": "fruit",
    "difficulty": 1,
    "type": "normal",
    "bonus_coin_multiplier": 1,
    "createTime": "2026-04-24 17:34:39",
    "generateTime": "2026-04-24 17:34:39",
    "version": "1.0",
    "dimension": 9,
    "rows": 9,
    "cols": 7,
    "useHardDirections": false,
    "sizeFactor": 4,
    "intersectBias": -1,
    "gridString": "ESUCHJP|LGNUBAE|PNRDPBA|PTZAVHN|ACYYOEA|EAULZNN|NGDEWFA|IZYEGXB|PDYDUTS",
    "words": [
        "HOLD",
        "HURT",
        "PINEAPPLE",
        "BANANA",
        "PAPAYA"
    ],
    "wordPositions": [
        {
            "word": "HOLD",
            "startX": 5,
            "startY": 3,
            "directionX": -1,
            "directionY": 1,
            "cellPositions": [
                {
                    "x": 5,
                    "y": 3
                },
                {
                    "x": 4,
                    "y": 4
                },
                {
                    "x": 3,
                    "y": 5
                },
                {
                    "x": 2,
                    "y": 6
                }
            ],
            "wordColor": {
                "r": 1.0,
                "g": 0.0,
                "b": 0.0,
                "a": 0.6000000238418579
            }
        },
        {
            "word": "HURT",
            "startX": 4,
            "startY": 0,
            "directionX": -1,
            "directionY": 1,
            "cellPositions": [
                {
                    "x": 4,
                    "y": 0
                },
                {
                    "x": 3,
                    "y": 1
                },
                {
                    "x": 2,
                    "y": 2
                },
                {
                    "x": 1,
                    "y": 3
                }
            ],
            "wordColor": {
                "r": 0.0,
                "g": 0.5,
                "b": 1.0,
                "a": 0.6000000238418579
            }
        },
        {
            "word": "PINEAPPLE",
            "startX": 0,
            "startY": 8,
            "directionX": 0,
            "directionY": -1,
            "cellPositions": [
                {
                    "x": 0,
                    "y": 8
                },
                {
                    "x": 0,
                    "y": 7
                },
                {
                    "x": 0,
                    "y": 6
                },
                {
                    "x": 0,
                    "y": 5
                },
                {
                    "x": 0,
                    "y": 4
                },
                {
                    "x": 0,
                    "y": 3
                },
                {
                    "x": 0,
                    "y": 2
                },
                {
                    "x": 0,
                    "y": 1
                },
                {
                    "x": 0,
                    "y": 0
                }
            ],
            "wordColor": {
                "r": 0.0,
                "g": 0.800000011920929,
                "b": 0.0,
                "a": 0.6000000238418579
            }
        },
        {
            "word": "BANANA",
            "startX": 6,
            "startY": 7,
            "directionX": 0,
            "directionY": -1,
            "cellPositions": [
                {
                    "x": 6,
                    "y": 7
                },
                {
                    "x": 6,
                    "y": 6
                },
                {
                    "x": 6,
                    "y": 5
                },
                {
                    "x": 6,
                    "y": 4
                },
                {
                    "x": 6,
                    "y": 3
                },
                {
                    "x": 6,
                    "y": 2
                }
            ],
            "wordColor": {
                "r": 1.0,
                "g": 0.6000000238418579,
                "b": 0.0,
                "a": 0.6000000238418579
            }
        },
        {
            "word": "PAPAYA",
            "startX": 6,
            "startY": 0,
            "directionX": -1,
            "directionY": 1,
            "cellPositions": [
                {
                    "x": 6,
                    "y": 0
                },
                {
                    "x": 5,
                    "y": 1
                },
                {
                    "x": 4,
                    "y": 2
                },
                {
                    "x": 3,
                    "y": 3
                },
                {
                    "x": 2,
                    "y": 4
                },
                {
                    "x": 1,
                    "y": 5
                }
            ],
            "wordColor": {
                "r": 0.6000000238418579,
                "g": 0.0,
                "b": 1.0,
                "a": 0.6000000238418579
            }
        }
    ],
    "bonusWords": [],
    "hiddenWords": [
        {
            "word": "STUDY",
            "startX": 6,
            "startY": 8,
            "directionX": -1,
            "directionY": 0,
            "cellPositions": [
                {
                    "x": 6,
                    "y": 8
                },
                {
                    "x": 5,
                    "y": 8
                },
                {
                    "x": 4,
                    "y": 8
                },
                {
                    "x": 3,
                    "y": 8
                },
                {
                    "x": 2,
                    "y": 8
                }
            ],
            "wordColor": {
                "r": 0.25,
                "g": 0.25,
                "b": 0.25,
                "a": 0.6000000238418579
            }
        },
        {
            "word": "SUCH",
            "startX": 1,
            "startY": 0,
            "directionX": 1,
            "directionY": 0,
            "cellPositions": [
                {
                    "x": 1,
                    "y": 0
                },
                {
                    "x": 2,
                    "y": 0
                },
                {
                    "x": 3,
                    "y": 0
                },
                {
                    "x": 4,
                    "y": 0
                }
            ],
            "wordColor": {
                "r": 0.25,
                "g": 0.25,
                "b": 0.25,
                "a": 0.6000000238418579
            }
        }
    ],
    "puzzleText": "E S U C H J P\nL G N U B A E\nP N R D P B A\nP T Z A V H N\nA C Y Y O E A\nE A U L Z N N\nN G D E W F A\nI Z Y E G X B\nP D Y D U T S",
    "answerKeyText": "e S u c H j P\nl g n u b a e\np n r d p b a\np t z a v H n\na c y y o e a\ne a u l z n n\nn g d e w f a\ni z y e g x B\nP d y d u t S",
    "seed": 2120232864,
    "bestOfN": 3,
    "layoutScore": 3.2529454231262209,
    "difficultyAuto": 43.69047546386719,
    "intersectionRatio": 0.1428571492433548,
    "directionDiversity": 0.5,
    "reverseRatio": 0.8571428656578064,
    "diagonalRatio": 0.4285714328289032,
    "wordDensity": 0.5873016119003296,
    "adjacentPairs": 26,
    "frameCoverage": 1.0,
    "xCrossCount": 0,
    "centroidBias": 0.06756752729415894,
    "pairwiseDistVar": 0.031089436262845994,
    "placementSequence": [
        "PINEAPPLE",
        "BANANA",
        "PAPAYA",
        "STUDY",
        "HOLD",
        "HURT",
        "SUCH"
    ]
}